gorps/__init__.py
gorps/__main__.py
gorps/cli.py
gorps/img_actions.py
gorps/load.py
gorps/log.py
gorps/model.py
gorps/py.typed
gorps/content_types/__init__.py
gorps/content_types/cooklang.py
gorps/exporters/__init__.py
gorps/exporters/base.py
gorps/exporters/cooklang.py
gorps/exporters/html.py
gorps/exporters/md.py
gorps/exporters/openrecipes.py
gorps/exporters/openrecipes_xml.py
gorps/exporters/serialize.py
gorps/exporters/svg.py
gorps/exporters/xml.py
gorps/exporters/yml.py
gorps/exporters/templating/__init__.py
gorps/exporters/templating/exporter.py
gorps/importers/__init__.py
gorps/importers/cooklang.py
gorps/importers/grmt.py
gorps/importers/yml.py
gorps/importers/deserialize/__init__.py
gorps/importers/deserialize/primitive_dict.py
gorps-1.0.1.dist-info/LICENSE
gorps-1.0.1.dist-info/METADATA
gorps-1.0.1.dist-info/WHEEL
gorps-1.0.1.dist-info/entry_points.txt
gorps-1.0.1.dist-info/top_level.txt
gorps-1.0.1.dist-info/RECORD
