Metadata-Version: 2.1
Name: gorps
Version: 1.0.1
Summary: Recipy converter
Author-email: Gerhard Bräunlich <g.braeunlich@disroot.org>
License:                     GNU GENERAL PUBLIC LICENSE
Project-URL: Repository, https://gitlab.com/g-braeunlich/gorps
Keywords: cooking
Classifier: Programming Language :: Python :: 3
Classifier: License :: OSI Approved :: GNU General Public License v3 (GPLv3)
Classifier: Operating System :: OS Independent
Requires-Python: >=3.10
License-File: LICENSE
Requires-Dist: PyYAML
Provides-Extra: openrecipes
Requires-Dist: pillow; extra == "openrecipes"
Provides-Extra: dev
Requires-Dist: types-PyYAML; extra == "dev"
Requires-Dist: types-pillow; extra == "dev"
